Workbook

Sheet Raw_Data
A1: Brand | B1: Channel | C1: P&L Item | D1: Last Year ($) | E1: Budget ($) | F1: Actual ($)
A2: MAC | B2: Free Standing | C2: Gross Sales | D2: 116000 | E2: 142000 | F2: 149000
A3: MAC | B3: Free Standing | C3: Net Returns | D3: -320 | E3: -360 | F3: -370
A4: MAC | B4: Free Standing | C4: Net Sales Discounts | D4: -18780 | E4: -22080 | F4: -30530
A5: MAC | B5: Free Standing | C5: Net Bonification | D5: 0 | E5: 0 | F5: 0
A6: MAC | B6: Free Standing | C6: Cost of Goods | D6: 16160 | E6: 25200 | F6: 28890
A7: MAC | B7: Free Standing | C7: COGS All Other | D7: 1350 | E7: 1560 | F7: 1380
A8: MAC | B8: Free Standing | C8: Selling | D8: 25860 | E8: 29790 | F8: 34010
A9: MAC | B9: Free Standing | C9: Marketing | D9: 2780 | E9: 3120 | F9: 3380
A10: MAC | B10: Free Standing | C10: Advertising | D10: 4300 | E10: 10860 | F10: 7860
A11: MAC | B11: Free Standing | C11: Promotion | D11: 1600 | E11: 840 | F11: 1520
A12: MAC | B12: Free Standing | C12: Store Operating Costs | D12: 14770 | E12: 17290 | F12: 23020
A13: MAC | B13: Free Standing | C13: Shipping/Warehouse | D13: 800 | E13: 1140 | F13: 1770
... A391: Jo Malone London | B391: Specialty Multi | C391: Total Shared Services | D391: 70 | E391: 60 | F391: 70

Sheet 📊 KPI Dashboard
A1: BEAUTY PORTFOLIO — 5 KPI DASHBOARD
A3: Tracking: EBIT Margin · GP Margin · Discount Rate · Advertising Intensity · Revenue Growth
A4: Color Key: | B4: Input (editable) | C4: Formula | D4: Cross-sheet link
A6: KPI 1 — EBIT Margin % | Formula: EBIT ÷ Net Sales × 100
A7: KPI | B7: Last Year | C7: Budget | D7: Actual | E7: vs Budget | F7: Target | G7: Status | H7: Trend
A8: EBIT Margin % | B8: =IFERROR((((SUMIF(Raw_Data!C:C,"Gross Sales",Raw_Data!D:D)+SUMIF(Raw_Data!C:C,"Net Returns",Raw_Data!D:D)+SUMIF(Raw_Data!C:C,"Net Sales Discounts",Raw_Data!D:D)+SUMIF(Raw_Data!C:C,"Net Bonification",Raw_Data!D:D))-SUMIF(Raw_Data!C:C,"Cost of Goods",Raw_Data!D:D)-SUMIF(Raw_Data!C:C,"COGS All Other",Raw_Data!D:D))-SUMIF(Raw_Data!C:C,"Selling*",Raw_Data!D:D)-SUMIF(Raw_Data!C:C,"Marketing*",Raw_Data!D:D)-SUMIF(Raw_Data!C:C,"Advertising*",Raw_Data!D:D)-SUMIF(Raw_Data!C:C,"Promotion*",Raw_Data!D:D)-SUMIF(Raw_Data!C:C,"Store Operating Costs",Raw_Data!D:D)-SUMIF(Raw_Data!C:C,"Shipping/Warehouse*",Raw_Data!D:D)-SUMIF(Raw_Data!C:C,"Total Shared Services",Raw_Data!D:D))/(SUMIF(Raw_Data!C:C,"Gross Sales",Raw_Data!D:D)+SUMIF(Raw_Data!C:C,"Net Returns",Raw_Data!D:D)+SUMIF(Raw_Data!C:C,"Net Sales Discounts",Raw_Data!D:D)+SUMIF(Raw_Data!C:C,"Net Bonification",Raw_Data!D:D)),0) | C8: =IFERROR((((SUMIF(Raw_Data!C:C,"Gross Sales",Raw_Data!E:E)+SUMIF(Raw_Data!C:C,"Net Returns",Raw_Data!E:E)+SUMIF(Raw_Data!C:C,"Net Sales Discounts",Raw_Data!E:E)+SUMIF(Raw_Data!C:C,"Net Bonification",Raw_Data!E:E))-SUMIF(Raw_Data!C:C,"Cost of Goods",Raw_Data!E:E)-SUMIF(Raw_Data!C:C,"COGS All Other",Raw_Data!E:E))-SUMIF(Raw_Data!C:C,"Selling*",Raw_Data!E:E)-SUMIF(Raw_Data!C:C,"Marketing*",Raw_Data!E:E)-SUMIF(Raw_Data!C:C,"Advertising*",Raw_Data!E:E)-SUMIF(Raw_Data!C:C,"Promotion*",Raw_Data!E:E)-SUMIF(Raw_Data!C:C,"Store Operating Costs",Raw_Data!E:E)-SUMIF(Raw_Data!C:C,"Shipping/Warehouse*",Raw_Data!E:E)-SUMIF(Raw_Data!C:C,"Total Shared Services",Raw_Data!E:E))/(SUMIF(Raw_Data!C:C,"Gross Sales",Raw_Data!E:E)+SUMIF(Raw_Data!C:C,"Net Returns",Raw_Data!E:E)+SUMIF(Raw_Data!C:C,"Net Sales Discounts",Raw_Data!E:E)+SUMIF(Raw_Data!C:C,"Net Bonification",Raw_Data!E:E)),0) | D8: =IFERROR((((SUMIF(Raw_Data!C:C,"Gross Sales",Raw_Data!F:F)+SUMIF(Raw_Data!C:C,"Net Returns",Raw_Data!F:F)+SUMIF(Raw_Data!C:C,"Net Sales Discounts",Raw_Data!F:F)+SUMIF(Raw_Data!C:C,"Net Bonification",Raw_Data!F:F))-SUMIF(Raw_Data!C:C,"Cost of Goods",Raw_Data!F:F)-SUMIF(Raw_Data!C:C,"COGS All Other",Raw_Data!F:F))-SUMIF(Raw_Data!C:C,"Selling*",Raw_Data!F:F)-SUMIF(Raw_Data!C:C,"Marketing*",Raw_Data!F:F)-SUMIF(Raw_Data!C:C,"Advertising*",Raw_Data!F:F)-SUMIF(Raw_Data!C:C,"Promotion*",Raw_Data!F:F)-SUMIF(Raw_Data!C:C,"Store Operating Costs",Raw_Data!F:F)-SUMIF(Raw_Data!C:C,"Shipping/Warehouse*",Raw_Data!F:F)-SUMIF(Raw_Data!C:C,"Total Shared Services",Raw_Data!F:F))/(SUMIF(Raw_Data!C:C,"Gross Sales",Raw_Data!F:F)+SUMIF(Raw_Data!C:C,"Net Returns",Raw_Data!F:F)+SUMIF(Raw_Data!C:C,"Net Sales Discounts",Raw_Data!F:F)+SUMIF(Raw_Data!C:C,"Net Bonification",Raw_Data!F:F)),0) | E8: =IFERROR(D8-C8,0) | F8: 0.15 | G8: =IF(D8>=F8,"✓ On Target",IF(D8>=F8*0.85,"⚠ Near Target","✗ Below Target")) | H8: =IF(D8>B8,"▲","▼")
A11: KPI 2 — GP Margin % | Formula: Gross Profit ÷ Net Sales × 100
A12: KPI | B12: Last Year | C12: Budget | D12: Actual | E12: vs Budget | F12: Target | G12: Status | H12: Trend
A13: GP Margin % | B13: =IFERROR(((SUMIF(Raw_Data!C:C,"Gross Sales",Raw_Data!D:D)+SUMIF(Raw_Data!C:C,"Net Returns",Raw_Data!D:D)+SUMIF(Raw_Data!C:C,"Net Sales Discounts",Raw_Data!D:D)+SUMIF(Raw_Data!C:C,"Net Bonification",Raw_Data!D:D))-SUMIF(Raw_Data!C:C,"Cost of Goods",Raw_Data!D:D)-SUMIF(Raw_Data!C:C,"COGS All Other",Raw_Data!D:D))/(SUMIF(Raw_Data!C:C,"Gross Sales",Raw_Data!D:D)+SUMIF(Raw_Data!C:C,"Net Returns",Raw_Data!D:D)+SUMIF(Raw_Data!C:C,"Net Sales Discounts",Raw_Data!D:D)+SUMIF(Raw_Data!C:C,"Net Bonification",Raw_Data!D:D)),0) | C13: =IFERROR(((SUMIF(Raw_Data!C:C,"Gross Sales",Raw_Data!E:E)+SUMIF(Raw_Data!C:C,"Net Returns",Raw_Data!E:E)+SUMIF(Raw_Data!C:C,"Net Sales Discounts",Raw_Data!E:E)+SUMIF(Raw_Data!C:C,"Net Bonification",Raw_Data!E:E))-SUMIF(Raw_Data!C:C,"Cost of Goods",Raw_Data!E:E)-SUMIF(Raw_Data!C:C,"COGS All Other",Raw_Data!E:E))/(SUMIF(Raw_Data!C:C,"Gross Sales",Raw_Data!E:E)+SUMIF(Raw_Data!C:C,"Net Returns",Raw_Data!E:E)+SUMIF(Raw_Data!C:C,"Net Sales Discounts",Raw_Data!E:E)+SUMIF(Raw_Data!C:C,"Net Bonification",Raw_Data!E:E)),0) | D13: =IFERROR(((SUMIF(Raw_Data!C:C,"Gross Sales",Raw_Data!F:F)+SUMIF(Raw_Data!C:C,"Net Returns",Raw_Data!F:F)+SUMIF(Raw_Data!C:C,"Net Sales Discounts",Raw_Data!F:F)+SUMIF(Raw_Data!C:C,"Net Bonification",Raw_Data!F:F))-SUMIF(Raw_Data!C:C,"Cost of Goods",Raw_Data!F:F)-SUMIF(Raw_Data!C:C,"COGS All Other",Raw_Data!F:F))/(SUMIF(Raw_Data!C:C,"Gross Sales",Raw_Data!F:F)+SUMIF(Raw_Data!C:C,"Net Returns",Raw_Data!F:F)+SUMIF(Raw_Data!C:C,"Net Sales Discounts",Raw_Data!F:F)+SUMIF(Raw_Data!C:C,"Net Bonification",Raw_Data!F:F)),0) | E13: =IFERROR(D13-C13,0) | F13: 0.68 | G13: =IF(D13>=F13,"✓ On Target",IF(D13>=F13*0.97,"⚠ Near Target","✗ Below Target")) | H13: =IF(D13>B13,"▲","▼")
A16: KPI 3 — Discount Rate % | Formula: Net Sales Discounts ÷ Gross Sales × 100
A17: KPI | B17: Last Year | C17: Budget | D17: Actual | E17: vs Budget | F17: Target | G17: Status | H17: Trend
A18: Discount Rate % | B18: =IFERROR(ABS(SUMIF(Raw_Data!C:C,"Net Sales Discounts",Raw_Data!D:D))/ABS((SUMIF(Raw_Data!C:C,"Gross Sales",Raw_Data!D:D))),0) | C18: =IFERROR(ABS(SUMIF(Raw_Data!C:C,"Net Sales Discounts",Raw_Data!E:E))/ABS((SUMIF(Raw_Data!C:C,"Gross Sales",Raw_Data!E:E))),0) | D18: =IFERROR(ABS(SUMIF(Raw_Data!C:C,"Net Sales Discounts",Raw_Data!F:F))/ABS((SUMIF(Raw_Data!C:C,"Gross Sales",Raw_Data!F:F))),0) | E18: =IFERROR(D18-C18,0) | F18: 0.28 | G18: =IF(D18<=F18,"✓ On Target",IF(D18<=F18*1.07,"⚠ Near Target","✗ Exceeds Target")) | H18: =IF(D18<B18,"▼ Improving","▲ Worsening")
A21: KPI 4 — Advertising Intensity % | Formula: (Advertising + Promotion) ÷ Net Sales × 100
A22: KPI | B22: Last Year | C22: Budget | D22: Actual | E22: vs Budget | F22: Target | G22: Status | H22: Trend
A23: Adv Intensity % | B23: =IFERROR((SUMIF(Raw_Data!C:C,"Advertising*",Raw_Data!D:D)+SUMIF(Raw_Data!C:C,"Promotion*",Raw_Data!D:D))/(SUMIF(Raw_Data!C:C,"Gross Sales",Raw_Data!D:D)+SUMIF(Raw_Data!C:C,"Net Returns",Raw_Data!D:D)+SUMIF(Raw_Data!C:C,"Net Sales Discounts",Raw_Data!D:D)+SUMIF(Raw_Data!C:C,"Net Bonification",Raw_Data!D:D)),0) | C23: =IFERROR((SUMIF(Raw_Data!C:C,"Advertising*",Raw_Data!E:E)+SUMIF(Raw_Data!C:C,"Promotion*",Raw_Data!E:E))/(SUMIF(Raw_Data!C:C,"Gross Sales",Raw_Data!E:E)+SUMIF(Raw_Data!C:C,"Net Returns",Raw_Data!E:E)+SUMIF(Raw_Data!C:C,"Net Sales Discounts",Raw_Data!E:E)+SUMIF(Raw_Data!C:C,"Net Bonification",Raw_Data!E:E)),0) | D23: =IFERROR((SUMIF(Raw_Data!C:C,"Advertising*",Raw_Data!F:F)+SUMIF(Raw_Data!C:C,"Promotion*",Raw_Data!F:F))/(SUMIF(Raw_Data!C:C,"Gross Sales",Raw_Data!F:F)+SUMIF(Raw_Data!C:C,"Net Returns",Raw_Data!F:F)+SUMIF(Raw_Data!C:C,"Net Sales Discounts",Raw_Data!F:F)+SUMIF(Raw_Data!C:C,"Net Bonification",Raw_Data!F:F)),0) | E23: =IFERROR(D23-C23,0) | F23: 0.13 | G23: =IF(D23<=F23,"✓ On Target",IF(D23<=F23*1.1,"⚠ Near Target","✗ Overspent")) | H23: =IF(D23<B23,"▼ Improving","▲ Worsening")
A26: KPI 5 — Revenue Growth % | Formula: (Actual GS − Last Year GS) ÷ Last Year GS × 100
A27: KPI | B27: Last Year | C27: Budget | D27: Actual | E27: vs Budget | F27: Target | G27: Status | H27: Trend
A28: Revenue Growth % | B28: "Base Year" | C28: =IFERROR(((SUMIF(Raw_Data!C:C,"Gross Sales",Raw_Data!E:E))-(SUMIF(Raw_Data!C:C,"Gross Sales",Raw_Data!D:D)))/(SUMIF(Raw_Data!C:C,"Gross Sales",Raw_Data!D:D)),0) | D28: =IFERROR(((SUMIF(Raw_Data!C:C,"Gross Sales",Raw_Data!F:F))-(SUMIF(Raw_Data!C:C,"Gross Sales",Raw_Data!D:D)))/(SUMIF(Raw_Data!C:C,"Gross Sales",Raw_Data!D:D)),0) | E28: =IFERROR(D28-C28,0) | F28: 0.25 | G28: =IF(D28>=F28,"✓ On Target",IF(D28>=F28*0.9,"⚠ Near Target","✗ Below Target")) | H28: =IF(D28>0,"▲ Growing","▼ Declining")
A31: ℹ Blue cells = editable targets (change to model different goals) | Black cells = live formulas pulling from Raw_Data | Green cells = cross-sheet SUMIF links

Sheet 📉 EBIT Bridge
A1: EBIT BRIDGE — Why did EBIT miss budget by $31K?
A3: Each line = Actual − Budget (and Actual − Last Year), signed by its effect on EBIT. Negative = hurt EBIT. All values are formulas from Raw_Data.
B5: P&L line | C5: Budget ($) | D5: Actual ($) | E5: Effect vs Budget ($) | F5: Last Year ($) | G5: Effect vs Last Year ($)
B6: Starting EBIT | C6: ='📊 KPI Dashboard'!C8*(SUMIF(Raw_Data!$C:$C,"Gross Sales",Raw_Data!$E:$E)+SUMIF(Raw_Data!$C:$C,"Net Returns",Raw_Data!$E:$E)+SUMIF(Raw_Data!$C:$C,"Net Sales Discounts",Raw_Data!$E:$E)+SUMIF(Raw_Data!$C:$C,"Net Bonification",Raw_Data!$E:$E)) | F6: ='📊 KPI Dashboard'!B8*(SUMIF(Raw_Data!$C:$C,"Gross Sales",Raw_Data!$D:$D)+SUMIF(Raw_Data!$C:$C,"Net Returns",Raw_Data!$D:$D)+SUMIF(Raw_Data!$C:$C,"Net Sales Discounts",Raw_Data!$D:$D)+SUMIF(Raw_Data!$C:$C,"Net Bonification",Raw_Data!$D:$D))
B7: Gross Sales | C7: =SUMIF(Raw_Data!$C:$C,"Gross Sales",Raw_Data!$E:$E) | D7: =SUMIF(Raw_Data!$C:$C,"Gross Sales",Raw_Data!$F:$F) | E7: =(D7-C7)*1 | F7: =SUMIF(Raw_Data!$C:$C,"Gross Sales",Raw_Data!$D:$D) | G7: =(D7-F7)*1
B8: Net Returns | C8: =SUMIF(Raw_Data!$C:$C,"Net Returns",Raw_Data!$E:$E) | D8: =SUMIF(Raw_Data!$C:$C,"Net Returns",Raw_Data!$F:$F) | E8: =(D8-C8)*1 | F8: =SUMIF(Raw_Data!$C:$C,"Net Returns",Raw_Data!$D:$D) | G8: =(D8-F8)*1
B9: Net Sales Discounts | C9: =SUMIF(Raw_Data!$C:$C,"Net Sales Discounts",Raw_Data!$E:$E) | D9: =SUMIF(Raw_Data!$C:$C,"Net Sales Discounts",Raw_Data!$F:$F) | E9: =(D9-C9)*1 | F9: =SUMIF(Raw_Data!$C:$C,"Net Sales Discounts",Raw_Data!$D:$D) | G9: =(D9-F9)*1
B10: Net Bonification | C10: =SUMIF(Raw_Data!$C:$C,"Net Bonification",Raw_Data!$E:$E) | D10: =SUMIF(Raw_Data!$C:$C,"Net Bonification",Raw_Data!$F:$F) | E10: =(D10-C10)*1 | F10: =SUMIF(Raw_Data!$C:$C,"Net Bonification",Raw_Data!$D:$D) | G10: =(D10-F10)*1
B11: Cost of Goods | C11: =SUMIF(Raw_Data!$C:$C,"Cost of Goods",Raw_Data!$E:$E) | D11: =SUMIF(Raw_Data!$C:$C,"Cost of Goods",Raw_Data!$F:$F) | E11: =(D11-C11)*-1 | F11: =SUMIF(Raw_Data!$C:$C,"Cost of Goods",Raw_Data!$D:$D) | G11: =(D11-F11)*-1
B12: COGS All Other | C12: =SUMIF(Raw_Data!$C:$C,"COGS All Other",Raw_Data!$E:$E) | D12: =SUMIF(Raw_Data!$C:$C,"COGS All Other",Raw_Data!$F:$F) | E12: =(D12-C12)*-1 | F12: =SUMIF(Raw_Data!$C:$C,"COGS All Other",Raw_Data!$D:$D) | G12: =(D12-F12)*-1
B13: Selling | C13: =SUMIF(Raw_Data!$C:$C,"Selling*",Raw_Data!$E:$E) | D13: =SUMIF(Raw_Data!$C:$C,"Selling*",Raw_Data!$F:$F) | E13: =(D13-C13)*-1 | F13: =SUMIF(Raw_Data!$C:$C,"Selling*",Raw_Data!$D:$D) | G13: =(D13-F13)*-1
B14: Marketing | C14: =SUMIF(Raw_Data!$C:$C,"Marketing*",Raw_Data!$E:$E) | D14: =SUMIF(Raw_Data!$C:$C,"Marketing*",Raw_Data!$F:$F) | E14: =(D14-C14)*-1 | F14: =SUMIF(Raw_Data!$C:$C,"Marketing*",Raw_Data!$D:$D) | G14: =(D14-F14)*-1
B15: Advertising | C15: =SUMIF(Raw_Data!$C:$C,"Advertising*",Raw_Data!$E:$E) | D15: =SUMIF(Raw_Data!$C:$C,"Advertising*",Raw_Data!$F:$F) | E15: =(D15-C15)*-1 | F15: =SUMIF(Raw_Data!$C:$C,"Advertising*",Raw_Data!$D:$D) | G15: =(D15-F15)*-1
B16: Promotion | C16: =SUMIF(Raw_Data!$C:$C,"Promotion*",Raw_Data!$E:$E) | D16: =SUMIF(Raw_Data!$C:$C,"Promotion*",Raw_Data!$F:$F) | E16: =(D16-C16)*-1 | F16: =SUMIF(Raw_Data!$C:$C,"Promotion*",Raw_Data!$D:$D) | G16: =(D16-F16)*-1
B17: Store Operating Costs | C17: =SUMIF(Raw_Data!$C:$C,"Store Operating Costs",Raw_Data!$E:$E) | D17: =SUMIF(Raw_Data!$C:$C,"Store Operating Costs",Raw_Data!$F:$F) | E17: =(D17-C17)*-1 | F17: =SUMIF(Raw_Data!$C:$C,"Store Operating Costs",Raw_Data!$D:$D) | G17: =(D17-F17)*-1
B18: Shipping/Warehouse | C18: =SUMIF(Raw_Data!$C:$C,"Shipping/Warehouse*",Raw_Data!$E:$E) | D18: =SUMIF(Raw_Data!$C:$C,"Shipping/Warehouse*",Raw_Data!$F:$F) | E18: =(D18-C18)*-1 | F18: =SUMIF(Raw_Data!$C:$C,"Shipping/Warehouse*",Raw_Data!$D:$D) | G18: =(D18-F18)*-1
B19: Total Shared Services | C19: =SUMIF(Raw_Data!$C:$C,"Total Shared Services",Raw_Data!$E:$E) | D19: =SUMIF(Raw_Data!$C:$C,"Total Shared Services",Raw_Data!$F:$F) | E19: =(D19-C19)*-1 | F19: =SUMIF(Raw_Data!$C:$C,"Total Shared Services",Raw_Data!$D:$D) | G19: =(D19-F19)*-1
B20: Total change in EBIT | E20: =SUM(E7:E19) | G20: =SUM(G7:G19)
B21: Actual EBIT (check: start + change) | D21: =C6+E20 | E21: =IF(ABS(D21-'📊 KPI Dashboard'!D8*(SUMIF(Raw_Data!$C:$C,"Gross Sales",Raw_Data!$F:$F)+SUMIF(Raw_Data!$C:$C,"Net Returns",Raw_Data!$F:$F)+SUMIF(Raw_Data!$C:$C,"Net Sales Discounts",Raw_Data!$F:$F)+SUMIF(Raw_Data!$C:$C,"Net Bonification",Raw_Data!$F:$F)))<1,"✓ ties to KPI Dashboard","✗ check")
A23: WHAT DROVE THE $31K MISS — grouped effect vs budget
B24: Driver | C24: Effect on EBIT ($)
B25: Extra gross sales | C25: =E7
B26: Higher discounts | C26: =E9
B27: Returns & bonification | C27: =E8+E10
B28: Cost of goods | C28: =E11+E12
B29: Selling costs | C29: =E13
B30: Advertising & promotion | C30: =E15+E16
B31: Store operating costs | C31: =E17
B32: Marketing, shipping, shared | C32: =E14+E18+E19

Sheet 🎯 Scenario Manager
A1: SCENARIO MANAGER — KPI Impact Analysis
A3: Adjust the blue assumptions per scenario. Net Sales = Gross Sales × (1 − Discount % − Returns & Bonification %); EBIT = Net Sales × (GP % − Adv Intensity %) − Other OpEx. The Base Case reproduces the actual P&L.
A5: STEP 1 — Enter Assumptions for Each Scenario (Blue = editable inputs)
A6: Assumption Driver | C6: Driver type | D6: Pessimistic | E6: Base Case (Current Actual) | F6: Optimistic
B7: Gross Sales ($) | C7: Revenue driver | D7: 450000 | E7: =SUMIF(Raw_Data!$C:$C,"Gross Sales",Raw_Data!$F:$F) | F7: 590000
B8: Discount Rate % | C8: Cash leakage | D8: 0.32 | E8: ='📊 KPI Dashboard'!D18 | F8: 0.26
B9: Advertising Intensity % | C9: Cost driver | D9: 0.19 | E9: ='📊 KPI Dashboard'!D23 | F9: 0.13
B10: Other OpEx ($) | C10: Selling, marketing, store, shipping, shared | D10: 155000 | E10: =(SUMIF(Raw_Data!$C:$C,"Selling*",Raw_Data!$F:$F)+SUMIF(Raw_Data!$C:$C,"Marketing*",Raw_Data!$F:$F)+SUMIF(Raw_Data!$C:$C,"Store Operating Costs",Raw_Data!$F:$F)+SUMIF(Raw_Data!$C:$C,"Shipping/Warehouse*",Raw_Data!$F:$F)+SUMIF(Raw_Data!$C:$C,"Total Shared Services",Raw_Data!$F:$F)) | F10: 130000
B11: Gross Profit Margin % | C11: Pricing power | D11: 0.62 | E11: ='📊 KPI Dashboard'!D13 | F11: 0.7
B12: Returns & Bonification % | C12: Sales deductions | D12: =E12 | E12: =-(SUMIF(Raw_Data!$C:$C,"Net Returns",Raw_Data!$F:$F)+SUMIF(Raw_Data!$C:$C,"Net Bonification",Raw_Data!$F:$F))/SUMIF(Raw_Data!$C:$C,"Gross Sales",Raw_Data!$F:$F) | F12: =E12
A13: STEP 2 — KPI Outputs (Formulas recalculate from assumptions above)
A14: KPI | D14: Pessimistic | E14: Base Case | F14: Optimistic | G14: Target
B15: EBIT Margin % | D15: =IFERROR(D11-D9-D10/(D7*(1-D8-D12)),0) | E15: =IFERROR(E11-E9-E10/(E7*(1-E8-E12)),0) | F15: =IFERROR(F11-F9-F10/(F7*(1-F8-F12)),0) | G15: ='📊 KPI Dashboard'!F8
B16: GP Margin % | D16: =D11 | E16: =E11 | F16: =F11 | G16: ='📊 KPI Dashboard'!F13
B17: Discount Rate % | D17: =D8 | E17: =E8 | F17: =F8 | G17: ='📊 KPI Dashboard'!F18
B18: Adv Intensity % | D18: =D9 | E18: =E9 | F18: =F9 | G18: ='📊 KPI Dashboard'!F23
B19: Revenue Growth % | D19: =IFERROR(D7/SUMIF(Raw_Data!$C:$C,"Gross Sales",Raw_Data!$D:$D)-1,0) | E19: =IFERROR(E7/SUMIF(Raw_Data!$C:$C,"Gross Sales",Raw_Data!$D:$D)-1,0) | F19: =IFERROR(F7/SUMIF(Raw_Data!$C:$C,"Gross Sales",Raw_Data!$D:$D)-1,0) | G19: ='📊 KPI Dashboard'!F28
D20: PESSIMISTIC | E20: BASE CASE | F20: OPTIMISTIC

Sheet 🎯 Goal Seek & What-If
A1: GOAL SEEK & WHAT-IF ANALYSIS — Sensitivity Tables
A3: What lever must change to achieve the EBIT Margin target of 15%? Two-variable data table: Discount Rate × Advertising Intensity → EBIT Margin
A5: PANEL A — Goal Seek Simulator: Required Gross Sales to Achieve EBIT Target
B6: Parameter | D6: Value (editable) | E6: Notes
B7: GP Margin % (fixed) | D7: ='📊 KPI Dashboard'!D13 | E7: Current actual GP margin
B8: Discount Rate % (fixed) | D8: ='📊 KPI Dashboard'!D18 | E8: Current actual discount rate
B9: Advertising Intensity % | D9: ='📊 KPI Dashboard'!D23 | E9: Current actual ad intensity
B10: Fixed Operating Costs ($) | D10: =(SUMIF(Raw_Data!$C:$C,"Selling*",Raw_Data!$F:$F)+SUMIF(Raw_Data!$C:$C,"Marketing*",Raw_Data!$F:$F)+SUMIF(Raw_Data!$C:$C,"Store Operating Costs",Raw_Data!$F:$F)+SUMIF(Raw_Data!$C:$C,"Shipping/Warehouse*",Raw_Data!$F:$F)+SUMIF(Raw_Data!$C:$C,"Total Shared Services",Raw_Data!$F:$F)) | E10: Selling + Marketing + Store + Shipping + Shared Services (actual)
B11: EBIT Margin Target | D11: ='📊 KPI Dashboard'!F8 | E11: ← Change this to see required Gross Sales
B12: Returns & Bonification % (fixed) | D12: =-(SUMIF(Raw_Data!$C:$C,"Net Returns",Raw_Data!$F:$F)+SUMIF(Raw_Data!$C:$C,"Net Bonification",Raw_Data!$F:$F))/SUMIF(Raw_Data!$C:$C,"Gross Sales",Raw_Data!$F:$F) | E12: Current actual share of gross sales
B13: ▶ Required Gross Sales | D13: =IFERROR(IF(D7-D9-D11<=0,"Not achievable",D10/((D7-D9-D11)*(1-D8-D12))),"Not achievable") | E13: Gross sales needed to hit the EBIT target at current margins and costs
A14: PANEL B — Two-Variable Sensitivity Table: EBIT Margin % by Discount Rate × Advertising Intensity
B15: EBIT Margin % for each Discount Rate (rows) × Advertising Intensity (columns), holding GP %, returns % and other OpEx at actuals and gross sales at the current $516.8K. Green ≥ 15% target, amber 10–15%, red < 10%.
B16: Discount Rate ↓ | Ad Intensity → | D16: 0.11 | E16: 0.12 | F16: 0.13 | G16: 0.14 | H16: 0.15 | I16: 0.16 | J16: 0.17 | K16: 0.18 | L16: 0.19
B17: 0.24 | D17: =IFERROR($D$7-D$16-$D$10/('🎯 Scenario Manager'!$E$7*(1-$B17-$D$12)),0) | E17: =IFERROR($D$7-E$16-$D$10/('🎯 Scenario Manager'!$E$7*(1-$B17-$D$12)),0) | F17: =IFERROR($D$7-F$16-$D$10/('🎯 Scenario Manager'!$E$7*(1-$B17-$D$12)),0) | G17: =IFERROR($D$7-G$16-$D$10/('🎯 Scenario Manager'!$E$7*(1-$B17-$D$12)),0) | H17: =IFERROR($D$7-H$16-$D$10/('🎯 Scenario Manager'!$E$7*(1-$B17-$D$12)),0) | I17: =IFERROR($D$7-I$16-$D$10/('🎯 Scenario Manager'!$E$7*(1-$B17-$D$12)),0) | J17: =IFERROR($D$7-J$16-$D$10/('🎯 Scenario Manager'!$E$7*(1-$B17-$D$12)),0) | K17: =IFERROR($D$7-K$16-$D$10/('🎯 Scenario Manager'!$E$7*(1-$B17-$D$12)),0) | L17: =IFERROR($D$7-L$16-$D$10/('🎯 Scenario Manager'!$E$7*(1-$B17-$D$12)),0)
B18: 0.26 | D18: =IFERROR($D$7-D$16-$D$10/('🎯 Scenario Manager'!$E$7*(1-$B18-$D$12)),0) | E18: =IFERROR($D$7-E$16-$D$10/('🎯 Scenario Manager'!$E$7*(1-$B18-$D$12)),0) | F18: =IFERROR($D$7-F$16-$D$10/('🎯 Scenario Manager'!$E$7*(1-$B18-$D$12)),0) | G18: =IFERROR($D$7-G$16-$D$10/('🎯 Scenario Manager'!$E$7*(1-$B18-$D$12)),0) | H18: =IFERROR($D$7-H$16-$D$10/('🎯 Scenario Manager'!$E$7*(1-$B18-$D$12)),0) | I18: =IFERROR($D$7-I$16-$D$10/('🎯 Scenario Manager'!$E$7*(1-$B18-$D$12)),0) | J18: =IFERROR($D$7-J$16-$D$10/('🎯 Scenario Manager'!$E$7*(1-$B18-$D$12)),0) | K18: =IFERROR($D$7-K$16-$D$10/('🎯 Scenario Manager'!$E$7*(1-$B18-$D$12)),0) | L18: =IFERROR($D$7-L$16-$D$10/('🎯 Scenario Manager'!$E$7*(1-$B18-$D$12)),0)
B19: 0.28 | D19: =IFERROR($D$7-D$16-$D$10/('🎯 Scenario Manager'!$E$7*(1-$B19-$D$12)),0) | E19: =IFERROR($D$7-E$16-$D$10/('🎯 Scenario Manager'!$E$7*(1-$B19-$D$12)),0) | F19: =IFERROR($D$7-F$16-$D$10/('🎯 Scenario Manager'!$E$7*(1-$B19-$D$12)),0) | G19: =IFERROR($D$7-G$16-$D$10/('🎯 Scenario Manager'!$E$7*(1-$B19-$D$12)),0) | H19: =IFERROR($D$7-H$16-$D$10/('🎯 Scenario Manager'!$E$7*(1-$B19-$D$12)),0) | I19: =IFERROR($D$7-I$16-$D$10/('🎯 Scenario Manager'!$E$7*(1-$B19-$D$12)),0) | J19: =IFERROR($D$7-J$16-$D$10/('🎯 Scenario Manager'!$E$7*(1-$B19-$D$12)),0) | K19: =IFERROR($D$7-K$16-$D$10/('🎯 Scenario Manager'!$E$7*(1-$B19-$D$12)),0) | L19: =IFERROR($D$7-L$16-$D$10/('🎯 Scenario Manager'!$E$7*(1-$B19-$D$12)),0)
B20: 0.3 | D20: =IFERROR($D$7-D$16-$D$10/('🎯 Scenario Manager'!$E$7*(1-$B20-$D$12)),0) | E20: =IFERROR($D$7-E$16-$D$10/('🎯 Scenario Manager'!$E$7*(1-$B20-$D$12)),0) | F20: =IFERROR($D$7-F$16-$D$10/('🎯 Scenario Manager'!$E$7*(1-$B20-$D$12)),0) | G20: =IFERROR($D$7-G$16-$D$10/('🎯 Scenario Manager'!$E$7*(1-$B20-$D$12)),0) | H20: =IFERROR($D$7-H$16-$D$10/('🎯 Scenario Manager'!$E$7*(1-$B20-$D$12)),0) | I20: =IFERROR($D$7-I$16-$D$10/('🎯 Scenario Manager'!$E$7*(1-$B20-$D$12)),0) | J20: =IFERROR($D$7-J$16-$D$10/('🎯 Scenario Manager'!$E$7*(1-$B20-$D$12)),0) | K20: =IFERROR($D$7-K$16-$D$10/('🎯 Scenario Manager'!$E$7*(1-$B20-$D$12)),0) | L20: =IFERROR($D$7-L$16-$D$10/('🎯 Scenario Manager'!$E$7*(1-$B20-$D$12)),0)
B21: 0.32 | D21: =IFERROR($D$7-D$16-$D$10/('🎯 Scenario Manager'!$E$7*(1-$B21-$D$12)),0) | E21: =IFERROR($D$7-E$16-$D$10/('🎯 Scenario Manager'!$E$7*(1-$B21-$D$12)),0) | F21: =IFERROR($D$7-F$16-$D$10/('🎯 Scenario Manager'!$E$7*(1-$B21-$D$12)),0) | G21: =IFERROR($D$7-G$16-$D$10/('🎯 Scenario Manager'!$E$7*(1-$B21-$D$12)),0) | H21: =IFERROR($D$7-H$16-$D$10/('🎯 Scenario Manager'!$E$7*(1-$B21-$D$12)),0) | I21: =IFERROR($D$7-I$16-$D$10/('🎯 Scenario Manager'!$E$7*(1-$B21-$D$12)),0) | J21: =IFERROR($D$7-J$16-$D$10/('🎯 Scenario Manager'!$E$7*(1-$B21-$D$12)),0) | K21: =IFERROR($D$7-K$16-$D$10/('🎯 Scenario Manager'!$E$7*(1-$B21-$D$12)),0) | L21: =IFERROR($D$7-L$16-$D$10/('🎯 Scenario Manager'!$E$7*(1-$B21-$D$12)),0)
B22: 0.34 | D22: =IFERROR($D$7-D$16-$D$10/('🎯 Scenario Manager'!$E$7*(1-$B22-$D$12)),0) | E22: =IFERROR($D$7-E$16-$D$10/('🎯 Scenario Manager'!$E$7*(1-$B22-$D$12)),0) | F22: =IFERROR($D$7-F$16-$D$10/('🎯 Scenario Manager'!$E$7*(1-$B22-$D$12)),0) | G22: =IFERROR($D$7-G$16-$D$10/('🎯 Scenario Manager'!$E$7*(1-$B22-$D$12)),0) | H22: =IFERROR($D$7-H$16-$D$10/('🎯 Scenario Manager'!$E$7*(1-$B22-$D$12)),0) | I22: =IFERROR($D$7-I$16-$D$10/('🎯 Scenario Manager'!$E$7*(1-$B22-$D$12)),0) | J22: =IFERROR($D$7-J$16-$D$10/('🎯 Scenario Manager'!$E$7*(1-$B22-$D$12)),0) | K22: =IFERROR($D$7-K$16-$D$10/('🎯 Scenario Manager'!$E$7*(1-$B22-$D$12)),0) | L22: =IFERROR($D$7-L$16-$D$10/('🎯 Scenario Manager'!$E$7*(1-$B22-$D$12)),0)
B23: 0.36 | D23: =IFERROR($D$7-D$16-$D$10/('🎯 Scenario Manager'!$E$7*(1-$B23-$D$12)),0) | E23: =IFERROR($D$7-E$16-$D$10/('🎯 Scenario Manager'!$E$7*(1-$B23-$D$12)),0) | F23: =IFERROR($D$7-F$16-$D$10/('🎯 Scenario Manager'!$E$7*(1-$B23-$D$12)),0) | G23: =IFERROR($D$7-G$16-$D$10/('🎯 Scenario Manager'!$E$7*(1-$B23-$D$12)),0) | H23: =IFERROR($D$7-H$16-$D$10/('🎯 Scenario Manager'!$E$7*(1-$B23-$D$12)),0) | I23: =IFERROR($D$7-I$16-$D$10/('🎯 Scenario Manager'!$E$7*(1-$B23-$D$12)),0) | J23: =IFERROR($D$7-J$16-$D$10/('🎯 Scenario Manager'!$E$7*(1-$B23-$D$12)),0) | K23: =IFERROR($D$7-K$16-$D$10/('🎯 Scenario Manager'!$E$7*(1-$B23-$D$12)),0) | L23: =IFERROR($D$7-L$16-$D$10/('🎯 Scenario Manager'!$E$7*(1-$B23-$D$12)),0)
A25: PANEL C — One-Variable Table: Required Gross Sales at Different EBIT Margin Targets (current: GP=66.4%, DR=29.8%, AI=17.0%)
B26: EBIT Target | D26: Required Gross Sales ($) | E26: Current Gross Sales ($) | F26: Change Needed ($) | G26: Verdict
B27: 0.08 | D27: =IFERROR(IF($D$7-$D$9-B27<=0,NA(),$D$10/(($D$7-$D$9-B27)*(1-$D$8-$D$12))),NA()) | E27: ='🎯 Scenario Manager'!$E$7 | F27: =D27-E27 | G27: =IFERROR(IF(F27<=0,"✓ At current sales","Needs +"&TEXT(F27/E27,"0%")&" sales"),"✗ Not achievable")
B28: 0.1 | D28: =IFERROR(IF($D$7-$D$9-B28<=0,NA(),$D$10/(($D$7-$D$9-B28)*(1-$D$8-$D$12))),NA()) | E28: ='🎯 Scenario Manager'!$E$7 | F28: =D28-E28 | G28: =IFERROR(IF(F28<=0,"✓ At current sales","Needs +"&TEXT(F28/E28,"0%")&" sales"),"✗ Not achievable")
B29: 0.12 | D29: =IFERROR(IF($D$7-$D$9-B29<=0,NA(),$D$10/(($D$7-$D$9-B29)*(1-$D$8-$D$12))),NA()) | E29: ='🎯 Scenario Manager'!$E$7 | F29: =D29-E29 | G29: =IFERROR(IF(F29<=0,"✓ At current sales","Needs +"&TEXT(F29/E29,"0%")&" sales"),"✗ Not achievable")
B30: 0.14 | D30: =IFERROR(IF($D$7-$D$9-B30<=0,NA(),$D$10/(($D$7-$D$9-B30)*(1-$D$8-$D$12))),NA()) | E30: ='🎯 Scenario Manager'!$E$7 | F30: =D30-E30 | G30: =IFERROR(IF(F30<=0,"✓ At current sales","Needs +"&TEXT(F30/E30,"0%")&" sales"),"✗ Not achievable")
B31: 0.15 | D31: =IFERROR(IF($D$7-$D$9-B31<=0,NA(),$D$10/(($D$7-$D$9-B31)*(1-$D$8-$D$12))),NA()) | E31: ='🎯 Scenario Manager'!$E$7 | F31: =D31-E31 | G31: =IFERROR(IF(F31<=0,"✓ At current sales","Needs +"&TEXT(F31/E31,"0%")&" sales"),"✗ Not achievable")
B32: 0.17 | D32: =IFERROR(IF($D$7-$D$9-B32<=0,NA(),$D$10/(($D$7-$D$9-B32)*(1-$D$8-$D$12))),NA()) | E32: ='🎯 Scenario Manager'!$E$7 | F32: =D32-E32 | G32: =IFERROR(IF(F32<=0,"✓ At current sales","Needs +"&TEXT(F32/E32,"0%")&" sales"),"✗ Not achievable")
B33: 0.2 | D33: =IFERROR(IF($D$7-$D$9-B33<=0,NA(),$D$10/(($D$7-$D$9-B33)*(1-$D$8-$D$12))),NA()) | E33: ='🎯 Scenario Manager'!$E$7 | F33: =D33-E33 | G33: =IFERROR(IF(F33<=0,"✓ At current sales","Needs +"&TEXT(F33/E33,"0%")&" sales"),"✗ Not achievable")

Sheet ⚙️ Decision Maker
A1: DECISION MAKER — Brand & Channel Profitability Ranking + Optimization
A3: Weighted scoring model to prioritize actions. Adjust weights (blue) to reflect your strategic priorities.
A5: PANEL A — Brand Profitability Scorecard (Data from Raw_Data via SUMIF)
B6: Brand | C6: Gross Sales | D6: Net Sales | E6: EBIT ($) | F6: EBIT Margin % | G6: GP Margin % | H6: Disc Rate % | I6: Rev Growth % | J6: Score /100 | K6: Recommendation
B7: MAC | C7: =SUMIFS(Raw_Data!F:F,Raw_Data!A:A,"MAC",Raw_Data!C:C,"Gross Sales") | D7: =IFERROR(SUMIFS(Raw_Data!F:F,Raw_Data!A:A,"MAC",Raw_Data!C:C,"Gross Sales")+SUMIFS(Raw_Data!F:F,Raw_Data!A:A,"MAC",Raw_Data!C:C,"Net Returns")+SUMIFS(Raw_Data!F:F,Raw_Data!A:A,"MAC",Raw_Data!C:C,"Net Sales Discounts")+SUMIFS(Raw_Data!F:F,Raw_Data!A:A,"MAC",Raw_Data!C:C,"Net Bonification"),0) | E7: =IFERROR(D7-(SUMIFS(Raw_Data!F:F,Raw_Data!A:A,"MAC",Raw_Data!C:C,"Cost of Goods")+SUMIFS(Raw_Data!F:F,Raw_Data!A:A,"MAC",Raw_Data!C:C,"COGS All Other"))-(SUMIFS(Raw_Data!F:F,Raw_Data!A:A,"MAC",Raw_Data!C:C,"Selling ")+SUMIFS(Raw_Data!F:F,Raw_Data!A:A,"MAC",Raw_Data!C:C,"Marketing ")+SUMIFS(Raw_Data!F:F,Raw_Data!A:A,"MAC",Raw_Data!C:C,"Advertising ")+SUMIFS(Raw_Data!F:F,Raw_Data!A:A,"MAC",Raw_Data!C:C,"Promotion ")+SUMIFS(Raw_Data!F:F,Raw_Data!A:A,"MAC",Raw_Data!C:C,"Store Operating Costs")+SUMIFS(Raw_Data!F:F,Raw_Data!A:A,"MAC",Raw_Data!C:C,"Shipping/Warehouse ")+SUMIFS(Raw_Data!F:F,Raw_Data!A:A,"MAC",Raw_Data!C:C,"Total Shared Services")),0) | F7: =IFERROR(E7/D7,0) | G7: =IFERROR((D7-(SUMIFS(Raw_Data!F:F,Raw_Data!A:A,"MAC",Raw_Data!C:C,"Cost of Goods")+SUMIFS(Raw_Data!F:F,Raw_Data!A:A,"MAC",Raw_Data!C:C,"COGS All Other")))/D7,0) | H7: =IFERROR(ABS(SUMIFS(Raw_Data!F:F,Raw_Data!A:A,"MAC",Raw_Data!C:C,"Net Sales Discounts"))/C7,0) | I7: =IFERROR((C7-(SUMIFS(Raw_Data!D:D,Raw_Data!A:A,"MAC",Raw_Data!C:C,"Gross Sales")))/(SUMIFS(Raw_Data!D:D,Raw_Data!A:A,"MAC",Raw_Data!C:C,"Gross Sales")),0) | J7: =IFERROR(MIN(100,MAX(0,(F7/0.25)*40 + (G7/0.7)*20 + (I7/0.4)*20 + (1-(H7/0.3))*20)),0) | K7: =IF(J7>=70,"✓ Invest & Grow",IF(J7>=45,"⚠ Optimise","✗ Review / Exit"))
B8: Estee Lauder | C8: =SUMIFS(Raw_Data!F:F,Raw_Data!A:A,"Estee Lauder",Raw_Data!C:C,"Gross Sales") | D8: =IFERROR(SUMIFS(Raw_Data!F:F,Raw_Data!A:A,"Estee Lauder",Raw_Data!C:C,"Gross Sales")+SUMIFS(Raw_Data!F:F,Raw_Data!A:A,"Estee Lauder",Raw_Data!C:C,"Net Returns")+SUMIFS(Raw_Data!F:F,Raw_Data!A:A,"Estee Lauder",Raw_Data!C:C,"Net Sales Discounts")+SUMIFS(Raw_Data!F:F,Raw_Data!A:A,"Estee Lauder",Raw_Data!C:C,"Net Bonification"),0) | E8: =IFERROR(D8-(SUMIFS(Raw_Data!F:F,Raw_Data!A:A,"Estee Lauder",Raw_Data!C:C,"Cost of Goods")+SUMIFS(Raw_Data!F:F,Raw_Data!A:A,"Estee Lauder",Raw_Data!C:C,"COGS All Other"))-(SUMIFS(Raw_Data!F:F,Raw_Data!A:A,"Estee Lauder",Raw_Data!C:C,"Selling ")+SUMIFS(Raw_Data!F:F,Raw_Data!A:A,"Estee Lauder",Raw_Data!C:C,"Marketing ")+SUMIFS(Raw_Data!F:F,Raw_Data!A:A,"Estee Lauder",Raw_Data!C:C,"Advertising ")+SUMIFS(Raw_Data!F:F,Raw_Data!A:A,"Estee Lauder",Raw_Data!C:C,"Promotion ")+SUMIFS(Raw_Data!F:F,Raw_Data!A:A,"Estee Lauder",Raw_Data!C:C,"Store Operating Costs")+SUMIFS(Raw_Data!F:F,Raw_Data!A:A,"Estee Lauder",Raw_Data!C:C,"Shipping/Warehouse ")+SUMIFS(Raw_Data!F:F,Raw_Data!A:A,"Estee Lauder",Raw_Data!C:C,"Total Shared Services")),0) | F8: =IFERROR(E8/D8,0) | G8: =IFERROR((D8-(SUMIFS(Raw_Data!F:F,Raw_Data!A:A,"Estee Lauder",Raw_Data!C:C,"Cost of Goods")+SUMIFS(Raw_Data!F:F,Raw_Data!A:A,"Estee Lauder",Raw_Data!C:C,"COGS All Other")))/D8,0) | H8: =IFERROR(ABS(SUMIFS(Raw_Data!F:F,Raw_Data!A:A,"Estee Lauder",Raw_Data!C:C,"Net Sales Discounts"))/C8,0) | I8: =IFERROR((C8-(SUMIFS(Raw_Data!D:D,Raw_Data!A:A,"Estee Lauder",Raw_Data!C:C,"Gross Sales")))/(SUMIFS(Raw_Data!D:D,Raw_Data!A:A,"Estee Lauder",Raw_Data!C:C,"Gross Sales")),0) | J8: =IFERROR(MIN(100,MAX(0,(F8/0.25)*40 + (G8/0.7)*20 + (I8/0.4)*20 + (1-(H8/0.3))*20)),0) | K8: =IF(J8>=70,"✓ Invest & Grow",IF(J8>=45,"⚠ Optimise","✗ Review / Exit"))
B9: Clinique | C9: =SUMIFS(Raw_Data!F:F,Raw_Data!A:A,"Clinique",Raw_Data!C:C,"Gross Sales") | D9: =IFERROR(SUMIFS(Raw_Data!F:F,Raw_Data!A:A,"Clinique",Raw_Data!C:C,"Gross Sales")+SUMIFS(Raw_Data!F:F,Raw_Data!A:A,"Clinique",Raw_Data!C:C,"Net Returns")+SUMIFS(Raw_Data!F:F,Raw_Data!A:A,"Clinique",Raw_Data!C:C,"Net Sales Discounts")+SUMIFS(Raw_Data!F:F,Raw_Data!A:A,"Clinique",Raw_Data!C:C,"Net Bonification"),0) | E9: =IFERROR(D9-(SUMIFS(Raw_Data!F:F,Raw_Data!A:A,"Clinique",Raw_Data!C:C,"Cost of Goods")+SUMIFS(Raw_Data!F:F,Raw_Data!A:A,"Clinique",Raw_Data!C:C,"COGS All Other"))-(SUMIFS(Raw_Data!F:F,Raw_Data!A:A,"Clinique",Raw_Data!C:C,"Selling ")+SUMIFS(Raw_Data!F:F,Raw_Data!A:A,"Clinique",Raw_Data!C:C,"Marketing ")+SUMIFS(Raw_Data!F:F,Raw_Data!A:A,"Clinique",Raw_Data!C:C,"Advertising ")+SUMIFS(Raw_Data!F:F,Raw_Data!A:A,"Clinique",Raw_Data!C:C,"Promotion ")+SUMIFS(Raw_Data!F:F,Raw_Data!A:A,"Clinique",Raw_Data!C:C,"Store Operating Costs")+SUMIFS(Raw_Data!F:F,Raw_Data!A:A,"Clinique",Raw_Data!C:C,"Shipping/Warehouse ")+SUMIFS(Raw_Data!F:F,Raw_Data!A:A,"Clinique",Raw_Data!C:C,"Total Shared Services")),0) | F9: =IFERROR(E9/D9,0) | G9: =IFERROR((D9-(SUMIFS(Raw_Data!F:F,Raw_Data!A:A,"Clinique",Raw_Data!C:C,"Cost of Goods")+SUMIFS(Raw_Data!F:F,Raw_Data!A:A,"Clinique",Raw_Data!C:C,"COGS All Other")))/D9,0) | H9: =IFERROR(ABS(SUMIFS(Raw_Data!F:F,Raw_Data!A:A,"Clinique",Raw_Data!C:C,"Net Sales Discounts"))/C9,0) | I9: =IFERROR((C9-(SUMIFS(Raw_Data!D:D,Raw_Data!A:A,"Clinique",Raw_Data!C:C,"Gross Sales")))/(SUMIFS(Raw_Data!D:D,Raw_Data!A:A,"Clinique",Raw_Data!C:C,"Gross Sales")),0) | J9: =IFERROR(MIN(100,MAX(0,(F9/0.25)*40 + (G9/0.7)*20 + (I9/0.4)*20 + (1-(H9/0.3))*20)),0) | K9: =IF(J9>=70,"✓ Invest & Grow",IF(J9>=45,"⚠ Optimise","✗ Review / Exit"))
B10: Tom Ford | C10: =SUMIFS(Raw_Data!F:F,Raw_Data!A:A,"Tom Ford",Raw_Data!C:C,"Gross Sales") | D10: =IFERROR(SUMIFS(Raw_Data!F:F,Raw_Data!A:A,"Tom Ford",Raw_Data!C:C,"Gross Sales")+SUMIFS(Raw_Data!F:F,Raw_Data!A:A,"Tom Ford",Raw_Data!C:C,"Net Returns")+SUMIFS(Raw_Data!F:F,Raw_Data!A:A,"Tom Ford",Raw_Data!C:C,"Net Sales Discounts")+SUMIFS(Raw_Data!F:F,Raw_Data!A:A,"Tom Ford",Raw_Data!C:C,"Net Bonification"),0) | E10: =IFERROR(D10-(SUMIFS(Raw_Data!F:F,Raw_Data!A:A,"Tom Ford",Raw_Data!C:C,"Cost of Goods")+SUMIFS(Raw_Data!F:F,Raw_Data!A:A,"Tom Ford",Raw_Data!C:C,"COGS All Other"))-(SUMIFS(Raw_Data!F:F,Raw_Data!A:A,"Tom Ford",Raw_Data!C:C,"Selling ")+SUMIFS(Raw_Data!F:F,Raw_Data!A:A,"Tom Ford",Raw_Data!C:C,"Marketing ")+SUMIFS(Raw_Data!F:F,Raw_Data!A:A,"Tom Ford",Raw_Data!C:C,"Advertising ")+SUMIFS(Raw_Data!F:F,Raw_Data!A:A,"Tom Ford",Raw_Data!C:C,"Promotion ")+SUMIFS(Raw_Data!F:F,Raw_Data!A:A,"Tom Ford",Raw_Data!C:C,"Store Operating Costs")+SUMIFS(Raw_Data!F:F,Raw_Data!A:A,"Tom Ford",Raw_Data!C:C,"Shipping/Warehouse ")+SUMIFS(Raw_Data!F:F,Raw_Data!A:A,"Tom Ford",Raw_Data!C:C,"Total Shared Services")),0) | F10: =IFERROR(E10/D10,0) | G10: =IFERROR((D10-(SUMIFS(Raw_Data!F:F,Raw_Data!A:A,"Tom Ford",Raw_Data!C:C,"Cost of Goods")+SUMIFS(Raw_Data!F:F,Raw_Data!A:A,"Tom Ford",Raw_Data!C:C,"COGS All Other")))/D10,0) | H10: =IFERROR(ABS(SUMIFS(Raw_Data!F:F,Raw_Data!A:A,"Tom Ford",Raw_Data!C:C,"Net Sales Discounts"))/C10,0) | I10: =IFERROR((C10-(SUMIFS(Raw_Data!D:D,Raw_Data!A:A,"Tom Ford",Raw_Data!C:C,"Gross Sales")))/(SUMIFS(Raw_Data!D:D,Raw_Data!A:A,"Tom Ford",Raw_Data!C:C,"Gross Sales")),0) | J10: =IFERROR(MIN(100,MAX(0,(F10/0.25)*40 + (G10/0.7)*20 + (I10/0.4)*20 + (1-(H10/0.3))*20)),0) | K10: =IF(J10>=70,"✓ Invest & Grow",IF(J10>=45,"⚠ Optimise","✗ Review / Exit"))
B11: The Ordinary | C11: =SUMIFS(Raw_Data!F:F,Raw_Data!A:A,"The Ordinary",Raw_Data!C:C,"Gross Sales") | D11: =IFERROR(SUMIFS(Raw_Data!F:F,Raw_Data!A:A,"The Ordinary",Raw_Data!C:C,"Gross Sales")+SUMIFS(Raw_Data!F:F,Raw_Data!A:A,"The Ordinary",Raw_Data!C:C,"Net Returns")+SUMIFS(Raw_Data!F:F,Raw_Data!A:A,"The Ordinary",Raw_Data!C:C,"Net Sales Discounts")+SUMIFS(Raw_Data!F:F,Raw_Data!A:A,"The Ordinary",Raw_Data!C:C,"Net Bonification"),0) | E11: =IFERROR(D11-(SUMIFS(Raw_Data!F:F,Raw_Data!A:A,"The Ordinary",Raw_Data!C:C,"Cost of Goods")+SUMIFS(Raw_Data!F:F,Raw_Data!A:A,"The Ordinary",Raw_Data!C:C,"COGS All Other"))-(SUMIFS(Raw_Data!F:F,Raw_Data!A:A,"The Ordinary",Raw_Data!C:C,"Selling ")+SUMIFS(Raw_Data!F:F,Raw_Data!A:A,"The Ordinary",Raw_Data!C:C,"Marketing ")+SUMIFS(Raw_Data!F:F,Raw_Data!A:A,"The Ordinary",Raw_Data!C:C,"Advertising ")+SUMIFS(Raw_Data!F:F,Raw_Data!A:A,"The Ordinary",Raw_Data!C:C,"Promotion ")+SUMIFS(Raw_Data!F:F,Raw_Data!A:A,"The Ordinary",Raw_Data!C:C,"Store Operating Costs")+SUMIFS(Raw_Data!F:F,Raw_Data!A:A,"The Ordinary",Raw_Data!C:C,"Shipping/Warehouse ")+SUMIFS(Raw_Data!F:F,Raw_Data!A:A,"The Ordinary",Raw_Data!C:C,"Total Shared Services")),0) | F11: =IFERROR(E11/D11,0) | G11: =IFERROR((D11-(SUMIFS(Raw_Data!F:F,Raw_Data!A:A,"The Ordinary",Raw_Data!C:C,"Cost of Goods")+SUMIFS(Raw_Data!F:F,Raw_Data!A:A,"The Ordinary",Raw_Data!C:C,"COGS All Other")))/D11,0) | H11: =IFERROR(ABS(SUMIFS(Raw_Data!F:F,Raw_Data!A:A,"The Ordinary",Raw_Data!C:C,"Net Sales Discounts"))/C11,0) | I11: =IFERROR((C11-(SUMIFS(Raw_Data!D:D,Raw_Data!A:A,"The Ordinary",Raw_Data!C:C,"Gross Sales")))/(SUMIFS(Raw_Data!D:D,Raw_Data!A:A,"The Ordinary",Raw_Data!C:C,"Gross Sales")),0) | J11: =IFERROR(MIN(100,MAX(0,(F11/0.25)*40 + (G11/0.7)*20 + (I11/0.4)*20 + (1-(H11/0.3))*20)),0) | K11: =IF(J11>=70,"✓ Invest & Grow",IF(J11>=45,"⚠ Optimise","✗ Review / Exit"))
B12: Jo Malone London | C12: =SUMIFS(Raw_Data!F:F,Raw_Data!A:A,"Jo Malone London",Raw_Data!C:C,"Gross Sales") | D12: =IFERROR(SUMIFS(Raw_Data!F:F,Raw_Data!A:A,"Jo Malone London",Raw_Data!C:C,"Gross Sales")+SUMIFS(Raw_Data!F:F,Raw_Data!A:A,"Jo Malone London",Raw_Data!C:C,"Net Returns")+SUMIFS(Raw_Data!F:F,Raw_Data!A:A,"Jo Malone London",Raw_Data!C:C,"Net Sales Discounts")+SUMIFS(Raw_Data!F:F,Raw_Data!A:A,"Jo Malone London",Raw_Data!C:C,"Net Bonification"),0) | E12: =IFERROR(D12-(SUMIFS(Raw_Data!F:F,Raw_Data!A:A,"Jo Malone London",Raw_Data!C:C,"Cost of Goods")+SUMIFS(Raw_Data!F:F,Raw_Data!A:A,"Jo Malone London",Raw_Data!C:C,"COGS All Other"))-(SUMIFS(Raw_Data!F:F,Raw_Data!A:A,"Jo Malone London",Raw_Data!C:C,"Selling ")+SUMIFS(Raw_Data!F:F,Raw_Data!A:A,"Jo Malone London",Raw_Data!C:C,"Marketing ")+SUMIFS(Raw_Data!F:F,Raw_Data!A:A,"Jo Malone London",Raw_Data!C:C,"Advertising ")+SUMIFS(Raw_Data!F:F,Raw_Data!A:A,"Jo Malone London",Raw_Data!C:C,"Promotion ")+SUMIFS(Raw_Data!F:F,Raw_Data!A:A,"Jo Malone London",Raw_Data!C:C,"Store Operating Costs")+SUMIFS(Raw_Data!F:F,Raw_Data!A:A,"Jo Malone London",Raw_Data!C:C,"Shipping/Warehouse ")+SUMIFS(Raw_Data!F:F,Raw_Data!A:A,"Jo Malone London",Raw_Data!C:C,"Total Shared Services")),0) | F12: =IFERROR(E12/D12,0) | G12: =IFERROR((D12-(SUMIFS(Raw_Data!F:F,Raw_Data!A:A,"Jo Malone London",Raw_Data!C:C,"Cost of Goods")+SUMIFS(Raw_Data!F:F,Raw_Data!A:A,"Jo Malone London",Raw_Data!C:C,"COGS All Other")))/D12,0) | H12: =IFERROR(ABS(SUMIFS(Raw_Data!F:F,Raw_Data!A:A,"Jo Malone London",Raw_Data!C:C,"Net Sales Discounts"))/C12,0) | I12: =IFERROR((C12-(SUMIFS(Raw_Data!D:D,Raw_Data!A:A,"Jo Malone London",Raw_Data!C:C,"Gross Sales")))/(SUMIFS(Raw_Data!D:D,Raw_Data!A:A,"Jo Malone London",Raw_Data!C:C,"Gross Sales")),0) | J12: =IFERROR(MIN(100,MAX(0,(F12/0.25)*40 + (G12/0.7)*20 + (I12/0.4)*20 + (1-(H12/0.3))*20)),0) | K12: =IF(J12>=70,"✓ Invest & Grow",IF(J12>=45,"⚠ Optimise","✗ Review / Exit"))
A14: PANEL B — Channel Profitability Scorecard
B15: Channel | C15: Gross Sales | D15: Net Sales | E15: EBIT ($) | F15: EBIT Margin % | G15: GP Margin % | H15: Disc Rate % | I15: EBIT vs Budget | J15: Score /100 | K15: Recommendation
B16: Free Standing | C16: =SUMIFS(Raw_Data!F:F,Raw_Data!B:B,"Free Standing",Raw_Data!C:C,"Gross Sales") | D16: =IFERROR(SUMIFS(Raw_Data!F:F,Raw_Data!B:B,"Free Standing",Raw_Data!C:C,"Gross Sales")+SUMIFS(Raw_Data!F:F,Raw_Data!B:B,"Free Standing",Raw_Data!C:C,"Net Returns")+SUMIFS(Raw_Data!F:F,Raw_Data!B:B,"Free Standing",Raw_Data!C:C,"Net Sales Discounts")+SUMIFS(Raw_Data!F:F,Raw_Data!B:B,"Free Standing",Raw_Data!C:C,"Net Bonification"),0) | E16: =IFERROR(D16-(SUMIFS(Raw_Data!F:F,Raw_Data!B:B,"Free Standing",Raw_Data!C:C,"Cost of Goods")+SUMIFS(Raw_Data!F:F,Raw_Data!B:B,"Free Standing",Raw_Data!C:C,"COGS All Other"))-(SUMIFS(Raw_Data!F:F,Raw_Data!B:B,"Free Standing",Raw_Data!C:C,"Selling ")+SUMIFS(Raw_Data!F:F,Raw_Data!B:B,"Free Standing",Raw_Data!C:C,"Marketing ")+SUMIFS(Raw_Data!F:F,Raw_Data!B:B,"Free Standing",Raw_Data!C:C,"Advertising ")+SUMIFS(Raw_Data!F:F,Raw_Data!B:B,"Free Standing",Raw_Data!C:C,"Promotion ")+SUMIFS(Raw_Data!F:F,Raw_Data!B:B,"Free Standing",Raw_Data!C:C,"Store Operating Costs")+SUMIFS(Raw_Data!F:F,Raw_Data!B:B,"Free Standing",Raw_Data!C:C,"Shipping/Warehouse ")+SUMIFS(Raw_Data!F:F,Raw_Data!B:B,"Free Standing",Raw_Data!C:C,"Total Shared Services")),0) | F16: =IFERROR(E16/D16,0) | G16: =IFERROR((D16-(SUMIFS(Raw_Data!F:F,Raw_Data!B:B,"Free Standing",Raw_Data!C:C,"Cost of Goods")+SUMIFS(Raw_Data!F:F,Raw_Data!B:B,"Free Standing",Raw_Data!C:C,"COGS All Other")))/D16,0) | H16: =IFERROR(ABS(SUMIFS(Raw_Data!F:F,Raw_Data!B:B,"Free Standing",Raw_Data!C:C,"Net Sales Discounts"))/C16,0) | I16: =IFERROR(E16-(SUMIFS(Raw_Data!E:E,Raw_Data!B:B,"Free Standing",Raw_Data!C:C,"Gross Sales")+SUMIFS(Raw_Data!E:E,Raw_Data!B:B,"Free Standing",Raw_Data!C:C,"Net Returns")+SUMIFS(Raw_Data!E:E,Raw_Data!B:B,"Free Standing",Raw_Data!C:C,"Net Sales Discounts")+SUMIFS(Raw_Data!E:E,Raw_Data!B:B,"Free Standing",Raw_Data!C:C,"Net Bonification")-SUMIFS(Raw_Data!E:E,Raw_Data!B:B,"Free Standing",Raw_Data!C:C,"Cost of Goods")-SUMIFS(Raw_Data!E:E,Raw_Data!B:B,"Free Standing",Raw_Data!C:C,"COGS All Other")-SUMIFS(Raw_Data!E:E,Raw_Data!B:B,"Free Standing",Raw_Data!C:C,"Selling ")-SUMIFS(Raw_Data!E:E,Raw_Data!B:B,"Free Standing",Raw_Data!C:C,"Marketing ")-SUMIFS(Raw_Data!E:E,Raw_Data!B:B,"Free Standing",Raw_Data!C:C,"Advertising ")-SUMIFS(Raw_Data!E:E,Raw_Data!B:B,"Free Standing",Raw_Data!C:C,"Promotion ")-SUMIFS(Raw_Data!E:E,Raw_Data!B:B,"Free Standing",Raw_Data!C:C,"Store Operating Costs")-SUMIFS(Raw_Data!E:E,Raw_Data!B:B,"Free Standing",Raw_Data!C:C,"Shipping/Warehouse ")-SUMIFS(Raw_Data!E:E,Raw_Data!B:B,"Free Standing",Raw_Data!C:C,"Total Shared Services")),0) | J16: =IFERROR(MIN(100,MAX(0,(F16/0.25)*40 + (G16/0.7)*20 +(1-(H16/0.35))*40)),0) | K16: =IF(J16>=65,"✓ Grow Channel",IF(J16>=35,"⚠ Optimise","✗ Exit / Renegotiate"))
B17: Brand com | C17: =SUMIFS(Raw_Data!F:F,Raw_Data!B:B,"Brand com",Raw_Data!C:C,"Gross Sales") | D17: =IFERROR(SUMIFS(Raw_Data!F:F,Raw_Data!B:B,"Brand com",Raw_Data!C:C,"Gross Sales")+SUMIFS(Raw_Data!F:F,Raw_Data!B:B,"Brand com",Raw_Data!C:C,"Net Returns")+SUMIFS(Raw_Data!F:F,Raw_Data!B:B,"Brand com",Raw_Data!C:C,"Net Sales Discounts")+SUMIFS(Raw_Data!F:F,Raw_Data!B:B,"Brand com",Raw_Data!C:C,"Net Bonification"),0) | E17: =IFERROR(D17-(SUMIFS(Raw_Data!F:F,Raw_Data!B:B,"Brand com",Raw_Data!C:C,"Cost of Goods")+SUMIFS(Raw_Data!F:F,Raw_Data!B:B,"Brand com",Raw_Data!C:C,"COGS All Other"))-(SUMIFS(Raw_Data!F:F,Raw_Data!B:B,"Brand com",Raw_Data!C:C,"Selling ")+SUMIFS(Raw_Data!F:F,Raw_Data!B:B,"Brand com",Raw_Data!C:C,"Marketing ")+SUMIFS(Raw_Data!F:F,Raw_Data!B:B,"Brand com",Raw_Data!C:C,"Advertising ")+SUMIFS(Raw_Data!F:F,Raw_Data!B:B,"Brand com",Raw_Data!C:C,"Promotion ")+SUMIFS(Raw_Data!F:F,Raw_Data!B:B,"Brand com",Raw_Data!C:C,"Store Operating Costs")+SUMIFS(Raw_Data!F:F,Raw_Data!B:B,"Brand com",Raw_Data!C:C,"Shipping/Warehouse ")+SUMIFS(Raw_Data!F:F,Raw_Data!B:B,"Brand com",Raw_Data!C:C,"Total Shared Services")),0) | F17: =IFERROR(E17/D17,0) | G17: =IFERROR((D17-(SUMIFS(Raw_Data!F:F,Raw_Data!B:B,"Brand com",Raw_Data!C:C,"Cost of Goods")+SUMIFS(Raw_Data!F:F,Raw_Data!B:B,"Brand com",Raw_Data!C:C,"COGS All Other")))/D17,0) | H17: =IFERROR(ABS(SUMIFS(Raw_Data!F:F,Raw_Data!B:B,"Brand com",Raw_Data!C:C,"Net Sales Discounts"))/C17,0) | I17: =IFERROR(E17-(SUMIFS(Raw_Data!E:E,Raw_Data!B:B,"Brand com",Raw_Data!C:C,"Gross Sales")+SUMIFS(Raw_Data!E:E,Raw_Data!B:B,"Brand com",Raw_Data!C:C,"Net Returns")+SUMIFS(Raw_Data!E:E,Raw_Data!B:B,"Brand com",Raw_Data!C:C,"Net Sales Discounts")+SUMIFS(Raw_Data!E:E,Raw_Data!B:B,"Brand com",Raw_Data!C:C,"Net Bonification")-SUMIFS(Raw_Data!E:E,Raw_Data!B:B,"Brand com",Raw_Data!C:C,"Cost of Goods")-SUMIFS(Raw_Data!E:E,Raw_Data!B:B,"Brand com",Raw_Data!C:C,"COGS All Other")-SUMIFS(Raw_Data!E:E,Raw_Data!B:B,"Brand com",Raw_Data!C:C,"Selling ")-SUMIFS(Raw_Data!E:E,Raw_Data!B:B,"Brand com",Raw_Data!C:C,"Marketing ")-SUMIFS(Raw_Data!E:E,Raw_Data!B:B,"Brand com",Raw_Data!C:C,"Advertising ")-SUMIFS(Raw_Data!E:E,Raw_Data!B:B,"Brand com",Raw_Data!C:C,"Promotion ")-SUMIFS(Raw_Data!E:E,Raw_Data!B:B,"Brand com",Raw_Data!C:C,"Store Operating Costs")-SUMIFS(Raw_Data!E:E,Raw_Data!B:B,"Brand com",Raw_Data!C:C,"Shipping/Warehouse ")-SUMIFS(Raw_Data!E:E,Raw_Data!B:B,"Brand com",Raw_Data!C:C,"Total Shared Services")),0) | J17: =IFERROR(MIN(100,MAX(0,(F17/0.25)*40 + (G17/0.7)*20 +(1-(H17/0.35))*40)),0) | K17: =IF(J17>=65,"✓ Grow Channel",IF(J17>=35,"⚠ Optimise","✗ Exit / Renegotiate"))
B18: Online 3PP | C18: =SUMIFS(Raw_Data!F:F,Raw_Data!B:B,"Online 3PP",Raw_Data!C:C,"Gross Sales") | D18: =IFERROR(SUMIFS(Raw_Data!F:F,Raw_Data!B:B,"Online 3PP",Raw_Data!C:C,"Gross Sales")+SUMIFS(Raw_Data!F:F,Raw_Data!B:B,"Online 3PP",Raw_Data!C:C,"Net Returns")+SUMIFS(Raw_Data!F:F,Raw_Data!B:B,"Online 3PP",Raw_Data!C:C,"Net Sales Discounts")+SUMIFS(Raw_Data!F:F,Raw_Data!B:B,"Online 3PP",Raw_Data!C:C,"Net Bonification"),0) | E18: =IFERROR(D18-(SUMIFS(Raw_Data!F:F,Raw_Data!B:B,"Online 3PP",Raw_Data!C:C,"Cost of Goods")+SUMIFS(Raw_Data!F:F,Raw_Data!B:B,"Online 3PP",Raw_Data!C:C,"COGS All Other"))-(SUMIFS(Raw_Data!F:F,Raw_Data!B:B,"Online 3PP",Raw_Data!C:C,"Selling ")+SUMIFS(Raw_Data!F:F,Raw_Data!B:B,"Online 3PP",Raw_Data!C:C,"Marketing ")+SUMIFS(Raw_Data!F:F,Raw_Data!B:B,"Online 3PP",Raw_Data!C:C,"Advertising ")+SUMIFS(Raw_Data!F:F,Raw_Data!B:B,"Online 3PP",Raw_Data!C:C,"Promotion ")+SUMIFS(Raw_Data!F:F,Raw_Data!B:B,"Online 3PP",Raw_Data!C:C,"Store Operating Costs")+SUMIFS(Raw_Data!F:F,Raw_Data!B:B,"Online 3PP",Raw_Data!C:C,"Shipping/Warehouse ")+SUMIFS(Raw_Data!F:F,Raw_Data!B:B,"Online 3PP",Raw_Data!C:C,"Total Shared Services")),0) | F18: =IFERROR(E18/D18,0) | G18: =IFERROR((D18-(SUMIFS(Raw_Data!F:F,Raw_Data!B:B,"Online 3PP",Raw_Data!C:C,"Cost of Goods")+SUMIFS(Raw_Data!F:F,Raw_Data!B:B,"Online 3PP",Raw_Data!C:C,"COGS All Other")))/D18,0) | H18: =IFERROR(ABS(SUMIFS(Raw_Data!F:F,Raw_Data!B:B,"Online 3PP",Raw_Data!C:C,"Net Sales Discounts"))/C18,0) | I18: =IFERROR(E18-(SUMIFS(Raw_Data!E:E,Raw_Data!B:B,"Online 3PP",Raw_Data!C:C,"Gross Sales")+SUMIFS(Raw_Data!E:E,Raw_Data!B:B,"Online 3PP",Raw_Data!C:C,"Net Returns")+SUMIFS(Raw_Data!E:E,Raw_Data!B:B,"Online 3PP",Raw_Data!C:C,"Net Sales Discounts")+SUMIFS(Raw_Data!E:E,Raw_Data!B:B,"Online 3PP",Raw_Data!C:C,"Net Bonification")-SUMIFS(Raw_Data!E:E,Raw_Data!B:B,"Online 3PP",Raw_Data!C:C,"Cost of Goods")-SUMIFS(Raw_Data!E:E,Raw_Data!B:B,"Online 3PP",Raw_Data!C:C,"COGS All Other")-SUMIFS(Raw_Data!E:E,Raw_Data!B:B,"Online 3PP",Raw_Data!C:C,"Selling ")-SUMIFS(Raw_Data!E:E,Raw_Data!B:B,"Online 3PP",Raw_Data!C:C,"Marketing ")-SUMIFS(Raw_Data!E:E,Raw_Data!B:B,"Online 3PP",Raw_Data!C:C,"Advertising ")-SUMIFS(Raw_Data!E:E,Raw_Data!B:B,"Online 3PP",Raw_Data!C:C,"Promotion ")-SUMIFS(Raw_Data!E:E,Raw_Data!B:B,"Online 3PP",Raw_Data!C:C,"Store Operating Costs")-SUMIFS(Raw_Data!E:E,Raw_Data!B:B,"Online 3PP",Raw_Data!C:C,"Shipping/Warehouse ")-SUMIFS(Raw_Data!E:E,Raw_Data!B:B,"Online 3PP",Raw_Data!C:C,"Total Shared Services")),0) | J18: =IFERROR(MIN(100,MAX(0,(F18/0.25)*40 + (G18/0.7)*20 +(1-(H18/0.35))*40)),0) | K18: =IF(J18>=65,"✓ Grow Channel",IF(J18>=35,"⚠ Optimise","✗ Exit / Renegotiate"))
B19: Department Stores | C19: =SUMIFS(Raw_Data!F:F,Raw_Data!B:B,"Department Stores",Raw_Data!C:C,"Gross Sales") | D19: =IFERROR(SUMIFS(Raw_Data!F:F,Raw_Data!B:B,"Department Stores",Raw_Data!C:C,"Gross Sales")+SUMIFS(Raw_Data!F:F,Raw_Data!B:B,"Department Stores",Raw_Data!C:C,"Net Returns")+SUMIFS(Raw_Data!F:F,Raw_Data!B:B,"Department Stores",Raw_Data!C:C,"Net Sales Discounts")+SUMIFS(Raw_Data!F:F,Raw_Data!B:B,"Department Stores",Raw_Data!C:C,"Net Bonification"),0) | E19: =IFERROR(D19-(SUMIFS(Raw_Data!F:F,Raw_Data!B:B,"Department Stores",Raw_Data!C:C,"Cost of Goods")+SUMIFS(Raw_Data!F:F,Raw_Data!B:B,"Department Stores",Raw_Data!C:C,"COGS All Other"))-(SUMIFS(Raw_Data!F:F,Raw_Data!B:B,"Department Stores",Raw_Data!C:C,"Selling ")+SUMIFS(Raw_Data!F:F,Raw_Data!B:B,"Department Stores",Raw_Data!C:C,"Marketing ")+SUMIFS(Raw_Data!F:F,Raw_Data!B:B,"Department Stores",Raw_Data!C:C,"Advertising ")+SUMIFS(Raw_Data!F:F,Raw_Data!B:B,"Department Stores",Raw_Data!C:C,"Promotion ")+SUMIFS(Raw_Data!F:F,Raw_Data!B:B,"Department Stores",Raw_Data!C:C,"Store Operating Costs")+SUMIFS(Raw_Data!F:F,Raw_Data!B:B,"Department Stores",Raw_Data!C:C,"Shipping/Warehouse ")+SUMIFS(Raw_Data!F:F,Raw_Data!B:B,"Department Stores",Raw_Data!C:C,"Total Shared Services")),0) | F19: =IFERROR(E19/D19,0) | G19: =IFERROR((D19-(SUMIFS(Raw_Data!F:F,Raw_Data!B:B,"Department Stores",Raw_Data!C:C,"Cost of Goods")+SUMIFS(Raw_Data!F:F,Raw_Data!B:B,"Department Stores",Raw_Data!C:C,"COGS All Other")))/D19,0) | H19: =IFERROR(ABS(SUMIFS(Raw_Data!F:F,Raw_Data!B:B,"Department Stores",Raw_Data!C:C,"Net Sales Discounts"))/C19,0) | I19: =IFERROR(E19-(SUMIFS(Raw_Data!E:E,Raw_Data!B:B,"Department Stores",Raw_Data!C:C,"Gross Sales")+SUMIFS(Raw_Data!E:E,Raw_Data!B:B,"Department Stores",Raw_Data!C:C,"Net Returns")+SUMIFS(Raw_Data!E:E,Raw_Data!B:B,"Department Stores",Raw_Data!C:C,"Net Sales Discounts")+SUMIFS(Raw_Data!E:E,Raw_Data!B:B,"Department Stores",Raw_Data!C:C,"Net Bonification")-SUMIFS(Raw_Data!E:E,Raw_Data!B:B,"Department Stores",Raw_Data!C:C,"Cost of Goods")-SUMIFS(Raw_Data!E:E,Raw_Data!B:B,"Department Stores",Raw_Data!C:C,"COGS All Other")-SUMIFS(Raw_Data!E:E,Raw_Data!B:B,"Department Stores",Raw_Data!C:C,"Selling ")-SUMIFS(Raw_Data!E:E,Raw_Data!B:B,"Department Stores",Raw_Data!C:C,"Marketing ")-SUMIFS(Raw_Data!E:E,Raw_Data!B:B,"Department Stores",Raw_Data!C:C,"Advertising ")-SUMIFS(Raw_Data!E:E,Raw_Data!B:B,"Department Stores",Raw_Data!C:C,"Promotion ")-SUMIFS(Raw_Data!E:E,Raw_Data!B:B,"Department Stores",Raw_Data!C:C,"Store Operating Costs")-SUMIFS(Raw_Data!E:E,Raw_Data!B:B,"Department Stores",Raw_Data!C:C,"Shipping/Warehouse ")-SUMIFS(Raw_Data!E:E,Raw_Data!B:B,"Department Stores",Raw_Data!C:C,"Total Shared Services")),0) | J19: =IFERROR(MIN(100,MAX(0,(F19/0.25)*40 + (G19/0.7)*20 +(1-(H19/0.35))*40)),0) | K19: =IF(J19>=65,"✓ Grow Channel",IF(J19>=35,"⚠ Optimise","✗ Exit / Renegotiate"))
B20: Specialty Multi | C20: =SUMIFS(Raw_Data!F:F,Raw_Data!B:B,"Specialty Multi",Raw_Data!C:C,"Gross Sales") | D20: =IFERROR(SUMIFS(Raw_Data!F:F,Raw_Data!B:B,"Specialty Multi",Raw_Data!C:C,"Gross Sales")+SUMIFS(Raw_Data!F:F,Raw_Data!B:B,"Specialty Multi",Raw_Data!C:C,"Net Returns")+SUMIFS(Raw_Data!F:F,Raw_Data!B:B,"Specialty Multi",Raw_Data!C:C,"Net Sales Discounts")+SUMIFS(Raw_Data!F:F,Raw_Data!B:B,"Specialty Multi",Raw_Data!C:C,"Net Bonification"),0) | E20: =IFERROR(D20-(SUMIFS(Raw_Data!F:F,Raw_Data!B:B,"Specialty Multi",Raw_Data!C:C,"Cost of Goods")+SUMIFS(Raw_Data!F:F,Raw_Data!B:B,"Specialty Multi",Raw_Data!C:C,"COGS All Other"))-(SUMIFS(Raw_Data!F:F,Raw_Data!B:B,"Specialty Multi",Raw_Data!C:C,"Selling ")+SUMIFS(Raw_Data!F:F,Raw_Data!B:B,"Specialty Multi",Raw_Data!C:C,"Marketing ")+SUMIFS(Raw_Data!F:F,Raw_Data!B:B,"Specialty Multi",Raw_Data!C:C,"Advertising ")+SUMIFS(Raw_Data!F:F,Raw_Data!B:B,"Specialty Multi",Raw_Data!C:C,"Promotion ")+SUMIFS(Raw_Data!F:F,Raw_Data!B:B,"Specialty Multi",Raw_Data!C:C,"Store Operating Costs")+SUMIFS(Raw_Data!F:F,Raw_Data!B:B,"Specialty Multi",Raw_Data!C:C,"Shipping/Warehouse ")+SUMIFS(Raw_Data!F:F,Raw_Data!B:B,"Specialty Multi",Raw_Data!C:C,"Total Shared Services")),0) | F20: =IFERROR(E20/D20,0) | G20: =IFERROR((D20-(SUMIFS(Raw_Data!F:F,Raw_Data!B:B,"Specialty Multi",Raw_Data!C:C,"Cost of Goods")+SUMIFS(Raw_Data!F:F,Raw_Data!B:B,"Specialty Multi",Raw_Data!C:C,"COGS All Other")))/D20,0) | H20: =IFERROR(ABS(SUMIFS(Raw_Data!F:F,Raw_Data!B:B,"Specialty Multi",Raw_Data!C:C,"Net Sales Discounts"))/C20,0) | I20: =IFERROR(E20-(SUMIFS(Raw_Data!E:E,Raw_Data!B:B,"Specialty Multi",Raw_Data!C:C,"Gross Sales")+SUMIFS(Raw_Data!E:E,Raw_Data!B:B,"Specialty Multi",Raw_Data!C:C,"Net Returns")+SUMIFS(Raw_Data!E:E,Raw_Data!B:B,"Specialty Multi",Raw_Data!C:C,"Net Sales Discounts")+SUMIFS(Raw_Data!E:E,Raw_Data!B:B,"Specialty Multi",Raw_Data!C:C,"Net Bonification")-SUMIFS(Raw_Data!E:E,Raw_Data!B:B,"Specialty Multi",Raw_Data!C:C,"Cost of Goods")-SUMIFS(Raw_Data!E:E,Raw_Data!B:B,"Specialty Multi",Raw_Data!C:C,"COGS All Other")-SUMIFS(Raw_Data!E:E,Raw_Data!B:B,"Specialty Multi",Raw_Data!C:C,"Selling ")-SUMIFS(Raw_Data!E:E,Raw_Data!B:B,"Specialty Multi",Raw_Data!C:C,"Marketing ")-SUMIFS(Raw_Data!E:E,Raw_Data!B:B,"Specialty Multi",Raw_Data!C:C,"Advertising ")-SUMIFS(Raw_Data!E:E,Raw_Data!B:B,"Specialty Multi",Raw_Data!C:C,"Promotion ")-SUMIFS(Raw_Data!E:E,Raw_Data!B:B,"Specialty Multi",Raw_Data!C:C,"Store Operating Costs")-SUMIFS(Raw_Data!E:E,Raw_Data!B:B,"Specialty Multi",Raw_Data!C:C,"Shipping/Warehouse ")-SUMIFS(Raw_Data!E:E,Raw_Data!B:B,"Specialty Multi",Raw_Data!C:C,"Total Shared Services")),0) | J20: =IFERROR(MIN(100,MAX(0,(F20/0.25)*40 + (G20/0.7)*20 +(1-(H20/0.35))*40)),0) | K20: =IF(J20>=65,"✓ Grow Channel",IF(J20>=35,"⚠ Optimise","✗ Exit / Renegotiate"))
A22: PANEL C — Solver / Optimization: EBIT Recovery Action Plan (editable targets in blue)
B23: Action | C23: KPI Lever | D23: Description | E23: Current | F23: Target | G23: Basis | H23: Est. EBIT Uplift ($) | I23: Priority | J23: Status
B24: Cap Advertising Spend | C24: Adv Intensity | D24: Cut ad + promo to 13% of net sales | E24: ='📊 KPI Dashboard'!D23 | F24: 0.13 | G24: Net Sales | H24: =(E24-F24)*SUM(D16:D20) | I24: 🔴 Critical | J24: In Progress
B25: Reduce Discount Rate | C25: Discount Rate | D25: Cut discounts to 27% of gross sales (volume held) | E25: ='📊 KPI Dashboard'!D18 | F25: 0.27 | G25: Gross Sales | H25: =(E25-F25)*SUM(C16:C20) | I25: 🔴 Critical | J25: Not Started
B26: Exit Specialty Multi | C26: EBIT Impact ($K) | D26: Remove Specialty Multi EBIT loss | E26: =E20 | F26: 0 | G26: EBIT ($K) | H26: =F26-E26 | I26: 🟡 High | J26: Under Review
B27: Shift 15% budget → Brand.com | C27: Revenue shift | D27: 15% of Spec. Multi → Brand.com | E27: 0.15 | F27: 0 | G27: EBIT uplift est. | H27: 3500 | I27: 🟡 High | J27: Not Started
B28: Clinique/Jo Malone OpEx cut | C28: OpEx reduction | D28: Target 10% cost reduction | E28: 1 | F28: 0.9 | G28: EBIT uplift est. | H28: 2000 | I28: 🟢 Medium | J28: Not Started
B29: TOTAL ESTIMATED EBIT RECOVERY (if all actions executed) | H29: =SUM(H24:H28)
B30: Note: rows 24–26 are calculated from the data; rows 27–28 are judgement estimates. Row 27 overlaps with row 26, so the total is an upper bound.
